rootly_mcp_server/__init__.py
rootly_mcp_server/__main__.py
rootly_mcp_server/client.py
rootly_mcp_server/server.py
rootly_mcp_server/smart_utils.py
rootly_mcp_server/texttest.json
rootly_mcp_server/utils.py
rootly_mcp_server/data/__init__.py
iflow_mcp_rootly_mcp_server-2.0.15.dist-info/METADATA
iflow_mcp_rootly_mcp_server-2.0.15.dist-info/WHEEL
iflow_mcp_rootly_mcp_server-2.0.15.dist-info/entry_points.txt
iflow_mcp_rootly_mcp_server-2.0.15.dist-info/licenses/LICENSE
iflow_mcp_rootly_mcp_server-2.0.15.dist-info/RECORD
