Metadata-Version: 2.4
Name: iflow-mcp_rootly-mcp-server
Version: 2.0.15
Summary: A Model Context Protocol server for Rootly APIs using OpenAPI spec
Project-URL: Homepage, https://github.com/Rootly-AI-Labs/Rootly-MCP-server
Project-URL: Issues, https://github.com/Rootly-AI-Labs/Rootly-MCP-server/issues
Author-email: Rootly AI Labs <support@rootly.com>
License-Expression: Apache-2.0
License-File: LICENSE
Keywords: automation,incidents,llm,mcp,rootly
Classifier: Development Status :: 5 - Production/Stable
Classifier: Intended Audience :: Developers
Classifier: Programming Language :: Python :: 3
Classifier: Programming Language :: Python :: 3.12
Classifier: Topic :: Software Development :: Build Tools
Requires-Python: >=3.12
Requires-Dist: brotli>=1.0.0
Requires-Dist: fastmcp>=2.9.0
Requires-Dist: httpx>=0.24.0
Requires-Dist: numpy>=1.24.0
Requires-Dist: pydantic>=2.0.0
Requires-Dist: requests>=2.28.0
Requires-Dist: scikit-learn>=1.3.0
Provides-Extra: dev
Requires-Dist: black>=23.0.0; extra == 'dev'
Requires-Dist: isort>=5.0.0; extra == 'dev'
